Metadata-Version: 2.1
Name: genai-translator-app
Version: 0.1
Summary: An AI-powered chatbot that leverages multiple open-source models, including Groq, for advanced language processing and translation.
Home-page: https://github.com/itsmohitkumar/GenAI-Translator
Author: Mohit Kumar
Author-email: mohitpanghal12345@gmail.com
License: UNKNOWN
Platform: UNKNOWN
Classifier: Programming Language :: Python :: 3
Classifier: License :: OSI Approved :: MIT License
Classifier: Operating System :: OS Independent
Classifier: Development Status :: 3 - Alpha
Classifier: Intended Audience :: Developers
Classifier: Topic :: Software Development :: Libraries :: Python Modules
Classifier: Topic :: Scientific/Engineering :: Artificial Intelligence
Requires-Python: >=3.9
Requires-Dist: langchain-groq
Requires-Dist: langchain-google-genai
Requires-Dist: langchain-openai
Requires-Dist: gradio
Requires-Dist: langdetect
Requires-Dist: python-dotenv
